threadx/__init__.py
threadx/threadx.py
threadx-0.1.0a3.dist-info/METADATA
threadx-0.1.0a3.dist-info/WHEEL
threadx-0.1.0a3.dist-info/licenses/LICENSE
threadx-0.1.0a3.dist-info/RECORD
