Metadata-Version: 2.4
Name: threadx
Version: 0.1.0a3
Summary: Chaining function calls on steroids
Project-URL: Homepage, https://github.com/withjak/threadx
Project-URL: Issues, https://github.com/withjak/threadx/issues
Author-email: Akshay Patel <akshaybishnoi@protonmail.com>
License:                                  Apache License
License-File: LICENSE
Keywords: chain,chaining,clojure,compose functions,data transformation,function chaining,functional programming,pipe,pipeline,threading
Classifier: License :: OSI Approved :: Apache Software License
Classifier: Operating System :: OS Independent
Classifier: Programming Language :: Python :: 3
Requires-Python: >=3.8
